aws_vpc/__init__.py
aws_vpc/aws_cdk/__init__.py
aws_vpc/aws_cdk/vpc_template.py
aws_vpc/troposphere/__init__.py
aws_vpc/troposphere/vpc_template.py
aws_vpc-2.0.0.dist-info/LICENSE.txt
aws_vpc-2.0.0.dist-info/METADATA
aws_vpc-2.0.0.dist-info/WHEEL
aws_vpc-2.0.0.dist-info/top_level.txt
aws_vpc-2.0.0.dist-info/RECORD
